[
  {
    "oneOf": [
      {
        "type": "string"
      },
      {
        "type": "number"
      },
      {
        "type": "boolean"
      }
    ]
  },
  {
    "oneOf": [
      {
        "type": "number",
        "const": 1
      },
      {
        "type": "number",
        "const": 3
      },
      {
        "type": "string",
        "const": "X"
      },
      {
        "type": "string",
        "const": "y"
      },
      {
        "type": "boolean",
        "const": false
      }
    ]
  },
  {
    "oneOf": [
      {
        "type": "object",
        "properties": {
          "a": {
            "type": "number",
            "const": 1
          }
        },
        "required": [
          "a"
        ]
      },
      {
        "type": "object",
        "properties": {
          "b": {
            "type": "number",
            "const": 1
          }
        },
        "required": [
          "b"
        ]
      },
      {
        "type": "string"
      }
    ]
  }
]